petio/sim/uart_top_sim.vhd
library ieee;
use ieee.std_logic_1164.all;
use ieee.numeric_std.all;

entity uart_top is
  Port (
    wb_clk_i : in std_logic;

    wb_rst_i : in std_logic;
    wb_adr_i : in std_logic_vector(2 downto 0);
    wb_dat_i : in std_logic_vector(7 downto 0);
    wb_dat_o : out std_logic_vector(7 downto 0);
    wb_we_i  : in std_logic;
    wb_stb_i : in std_logic;
    wb_cyc_i : in std_logic;

    int_o    : out std_logic;

    stx_pad_o : out std_logic;
    srx_pad_i : in std_logic;

    rts_pad_o : out std_logic;
    cts_pad_i : in std_logic;
    dtr_pad_o : out std_logic;
    dsr_pad_i : in std_logic;
    ri_pad_i  : in std_logic;
    dcd_pad_i : in std_logic
  );
end uart_top;

architecture sim of uart_top is
  type reg_array_t is array (0 to 7) of std_logic_vector(7 downto 0);
  signal regs : reg_array_t := (others => (others => '0'));
  signal addr_i : integer range 0 to 7;
begin
  addr_i <= to_integer(unsigned(wb_adr_i));

  process(wb_clk_i)
  begin
    if rising_edge(wb_clk_i) then
      if wb_rst_i = '1' then
        regs <= (others => (others => '0'));
        int_o <= '0';
      elsif wb_cyc_i = '1' and wb_stb_i = '1' and wb_we_i = '1' then
        regs(addr_i) <= wb_dat_i;
        int_o <= '1' when addr_i = 1 else '0';
      else
        int_o <= '0';
      end if;
    end if;
  end process;

  wb_dat_o <= regs(addr_i);

  stx_pad_o <= srx_pad_i;
  rts_pad_o <= not cts_pad_i;
  dtr_pad_o <= not (dsr_pad_i and ri_pad_i and dcd_pad_i);
end architecture;

petio/uart_shell.vhd
----------------------------------------------------------------------------------
-- Company: 
-- Engineer: 
-- 
-- Create Date:    22:45:16 04/10/2026 
-- Design Name: 
-- Module Name:    uart_shell - Behavioral 
-- Project Name: 
-- Target Devices: 
-- Tool versions: 
-- Description: 
--
-- Dependencies: 
--
-- Revision: 
-- Revision 0.01 - File Created
-- Additional Comments: 
--
----------------------------------------------------------------------------------
library IEEE;
use IEEE.STD_LOGIC_1164.ALL;

-- Uncomment the following library declaration if using
-- arithmetic functions with Signed or Unsigned values
--use IEEE.NUMERIC_STD.ALL;

-- Uncomment the following library declaration if instantiating
-- any Xilinx primitives in this code.
--library UNISIM;
--use UNISIM.VComponents.all;

entity uart_shell is
    Port ( phi2 : in  STD_LOGIC;
           qclk : in  STD_LOGIC;
           rwb : in  STD_LOGIC;
           nres : in  STD_LOGIC;
			  sel : in STD_LOGIC;
           addr : in  STD_LOGIC_VECTOR (2 downto 0);
           din : in  STD_LOGIC_VECTOR (7 downto 0);
           dout : out  STD_LOGIC_VECTOR (7 downto 0);
           irq : out  STD_LOGIC;
           rx : in  STD_LOGIC;
           tx : out  STD_LOGIC;
           cts : in  STD_LOGIC;
           rts : out  STD_LOGIC;
           dsr : in  STD_LOGIC;
           dtr : out  STD_LOGIC;
           ri : in  STD_LOGIC;
           dcd : in  STD_LOGIC);
end uart_shell;

architecture Behavioral of uart_shell is

	component uart_top is 
		Port (
			wb_clk_i : in std_logic;
	
			-- Wishbone signals
			wb_rst_i : in std_logic;
			wb_adr_i : in std_logic_vector(2 downto 0);
			wb_dat_i : in std_logic_vector(7 downto 0);
			wb_dat_o : out std_logic_vector(7 downto 0); 
			wb_we_i  : in std_logic;
			wb_stb_i : in std_logic; 
			wb_cyc_i : in std_logic; 
			
			-- interrupt request
			int_o		: out std_logic; 

			-- UART	signals
			-- serial input/output
			stx_pad_o : out std_logic; 
			srx_pad_i : in std_logic;
			
			-- modem signals
			rts_pad_o : out std_logic; 
			cts_pad_i : in std_logic;
			dtr_pad_o : out std_logic; 
			dsr_pad_i : in std_logic;
			ri_pad_i	 : in std_logic; 
			dcd_pad_i : in std_logic
		);
	end component;

		signal we: std_logic;
		signal stb: std_logic;
		signal cyc: std_logic;
		
begin

	uart_c: uart_top
		port map (
			qclk,
			not(nres),
			addr,
			din,
			dout,
			we,
			stb,
			cyc,
			irq,
			tx,
			rx,
			rts,
			cts,
			dtr,
			dsr,
			ri,
			dcd
		);

	cyc <= phi2;
	we <= not(rwb) and phi2;
	stb <= sel;
	
end Behavioral;

petio/sim/tb_uart_shell.vhd
library ieee;
use ieee.std_logic_1164.all;
use ieee.numeric_std.all;
use std.env.all;

use work.reg_script_pkg.all;

entity tb_uart_shell is
  generic (
    script_file : string := "scripts/uart_script.txt"
  );
end entity;

architecture tb of tb_uart_shell is
  signal phi2 : std_logic := '0';
  signal qclk : std_logic := '0';
  signal rwb  : std_logic := '1';
  signal nres : std_logic := '0';
  signal sel  : std_logic := '0';
  signal addr : std_logic_vector(2 downto 0) := (others => '0');
  signal din  : std_logic_vector(7 downto 0) := (others => '0');
  signal dout : std_logic_vector(7 downto 0);
  signal irq  : std_logic;

  signal rx  : std_logic := '1';
  signal tx  : std_logic;
  signal cts : std_logic := '0';
  signal rts : std_logic;
  signal dsr : std_logic := '0';
  signal dtr : std_logic;
  signal ri  : std_logic := '0';
  signal dcd : std_logic := '0';
begin
  dut: entity work.uart_shell
    port map (
      phi2 => phi2,
      qclk => qclk,
      rwb => rwb,
      nres => nres,
      sel => sel,
      addr => addr,
      din => din,
      dout => dout,
      irq => irq,
      rx => rx,
      tx => tx,
      cts => cts,
      rts => rts,
      dsr => dsr,
      dtr => dtr,
      ri => ri,
      dcd => dcd
    );

  clk_p: process
  begin
    loop
      phi2 <= '0';
      wait for 5 ns;
      phi2 <= '1';
      wait for 5 ns;
    end loop;
  end process;

  qclk_p: process
  begin
    loop
      qclk <= '0';
      wait for 1 ns;
      qclk <= '1';
      wait for 1 ns;
    end loop;
  end process;

  rst_p: process
  begin
    wait for 35 ns;
    nres <= '1';
    wait;
  end process;

  stim_p: process
    variable cmds      : cmd_array_t;
    variable cmd_count : natural := 0;
    variable cmd_idx   : natural := 0;
    variable cycle     : natural := 0;
    variable max_cycle : natural := 0;
    variable cmd       : cmd_t;
  begin
    init_cmds(cmds);
    load_script(script_file, cmds, cmd_count);

    if cmd_count > 0 then
      for i in 0 to cmd_count - 1 loop
        if cmds(i).cycle > max_cycle then
          max_cycle := cmds(i).cycle;
        end if;
      end loop;
    end if;

    wait until nres = '1';

    while cycle <= max_cycle + 4 loop
      wait until rising_edge(phi2);
      sel <= '0';
      rwb <= '1';

      if (cmd_idx < cmd_count) and cmds(cmd_idx).valid and (cmds(cmd_idx).cycle = cycle) then
        cmd := cmds(cmd_idx);
        addr <= to_slv(cmd.addr, 3);
        din <= cmd.data;

        case cmd.op is
          when OP_WRITE =>
            sel <= '1';
            rwb <= '0';
            report "UART cycle " & integer'image(integer(cycle)) & ": WRITE addr=" & integer'image(integer(cmd.addr)) &
                   " data=" & integer'image(to_integer(unsigned(cmd.data)));
          when OP_READ =>
            sel <= '1';
            rwb <= '1';
            report "UART cycle " & integer'image(integer(cycle)) & ": READ addr=" & integer'image(integer(cmd.addr));
          when others =>
            report "UART cycle " & integer'image(integer(cycle)) & ": PAUSE";
        end case;

        cmd_idx := cmd_idx + 1;
      end if;

      cycle := cycle + 1;
    end loop;

    report "UART simulation complete";
    finish;
  end process;
end architecture;

petio/sim/uart.vcd
$date
  Sat Sep 12 22:47:31 2026
$end
$version
  GHDL v0
$end
$timescale
  1 fs
$end
$scope module standard $end
$upscope $end
$scope module textio $end
$upscope $end
$scope module std_logic_1164 $end
$upscope $end
$scope module numeric_std $end
$upscope $end
$scope module env $end
$upscope $end
$scope module reg_script_pkg $end
$upscope $end
$scope module tb_uart_shell $end
$var reg 1 ! phi2 $end
$var reg 1 " qclk $end
$var reg 1 # rwb $end
$var reg 1 $ nres $end
$var reg 1 % sel $end
$var reg 3 & addr[2:0] $end
$var reg 8 ' din[7:0] $end
$var reg 8 ( dout[7:0] $end
$var reg 1 ) irq $end
$var reg 1 * rx $end
$var reg 1 + tx $end
$var reg 1 , cts $end
$var reg 1 - rts $end
$var reg 1 . dsr $end
$var reg 1 / dtr $end
$var reg 1 0 ri $end
$var reg 1 1 dcd $end
$scope module dut $end
$var reg 1 2 phi2 $end
$var reg 1 3 qclk $end
$var reg 1 4 rwb $end
$var reg 1 5 nres $end
$var reg 1 6 sel $end
$var reg 3 7 addr[2:0] $end
$var reg 8 8 din[7:0] $end
$var reg 8 9 dout[7:0] $end
$var reg 1 : irq $end
$var reg 1 ; rx $end
$var reg 1 < tx $end
$var reg 1 = cts $end
$var reg 1 > rts $end
$var reg 1 ? dsr $end
$var reg 1 @ dtr $end
$var reg 1 A ri $end
$var reg 1 B dcd $end
$var reg 1 C we $end
$var reg 1 D stb $end
$var reg 1 E cyc $end
$scope module uart_c $end
$var reg 1 F wb_clk_i $end
$var reg 1 G wb_rst_i $end
$var reg 3 H wb_adr_i[2:0] $end
$var reg 8 I wb_dat_i[7:0] $end
$var reg 8 J wb_dat_o[7:0] $end
$var reg 1 K wb_we_i $end
$var reg 1 L wb_stb_i $end
$var reg 1 M wb_cyc_i $end
$var reg 1 N int_o $end
$var reg 1 O stx_pad_o $end
$var reg 1 P srx_pad_i $end
$var reg 1 Q rts_pad_o $end
$var reg 1 R cts_pad_i $end
$var reg 1 S dtr_pad_o $end
$var reg 1 T dsr_pad_i $end
$var reg 1 U ri_pad_i $end
$var reg 1 V dcd_pad_i $end
$comment regs is not handled $end
$var integer 32 W addr_i $end
$upscope $end
$upscope $end
$upscope $end
$enddefinitions $end
#0
0!
0"
1#
0$
0%
b000 &
b00000000 '
b00000000 (
U)
1*
1+
0,
1-
0.
1/
00
01
02
03
14
05
06
b000 7
b00000000 8
b00000000 9
U:
1;
1<
0=
1>
0?
1@
0A
0B
0C
0D
0E
0F
1G
b000 H
b00000000 I
b00000000 J
0K
0L
0M
UN
1O
1P
1Q
0R
1S
0T
0U
0V
b0 W
#5000000
1!
1"
0)
12
13
0:
1E
1F
1M
0N
#10000000
0!
0"
02
03
0E
0F
0M
#15000000
1!
1"
12
13
1E
1F
1M
#20000000
0!
0"
02
03
0E
0F
0M
#25000000
1!
1"
12
13
1E
1F
1M
#30000000
0!
0"
02
03
0E
0F
0M
#35000000
1!
1"
1$
12
13
15
1E
1F
0G
1M
#40000000
0!
0"
02
03
0E
0F
0M
#45000000
1!
1"
0#
1%
b01000001 '
12
13
04
16
b01000001 8
1C
1D
1E
1F
b01000001 I
1K
1L
1M
#50000000
0!
0"
02
03
0E
0F
0M
#55000000
1!
1"
b001 &
b00000001 '
12
13
b001 7
b00000001 8
1E
1F
b001 H
b00000001 I
1M
b1 W
#60000000
0!
0"
02
03
0E
0F
0M
#65000000
1!
1"
1#
0%
b00000001 (
1)
12
13
14
06
b00000001 9
1:
0C
0D
1E
1F
b00000001 J
0K
0L
1M
1N
#70000000
0!
0"
02
03
0E
0F
0M
#75000000
1!
1"
1%
b000 &
b00000000 '
0)
12
13
16
b000 7
b00000000 8
0:
1D
1E
1F
b000 H
b00000000 I
1L
1M
0N
b0 W
#80000000
0!
0"
02
03
0E
0F
0M
#85000000
1!
1"
0%
12
13
06
0D
1E
1F
0L
1M
#90000000
0!
0"
02
03
0E
0F
0M
#95000000
1!
1"
12
13
1E
1F
1M
#100000000
0!
0"
02
03
0E
0F
0M
#105000000
1!
1"
12
13
1E
1F
1M
#110000000
0!
0"
02
03
0E
0F
0M
#115000000
1!
1"
0#
1%
b011 &
b10000000 '
b00000000 (
12
13
04
16
b011 7
b10000000 8
b00000000 9
1C
1D
1E
1F
b011 H
b10000000 I
b00000000 J
1K
1L
1M
b11 W
#120000000
0!
0"
02
03
0E
0F
0M
#125000000
1!
1"
1#
0%
b10000000 (
12
13
14
06
b10000000 9
0C
0D
1E
1F
b10000000 J
0K
0L
1M
#130000000
0!
0"
02
03
0E
0F
0M
#135000000
1!
1"
1%
b00000000 '
12
13
16
b00000000 8
1D
1E
1F
b00000000 I
1L
1M
#140000000
0!
0"
02
03
0E
0F
0M
#145000000
1!
1"
0%
12
13
06
0D
1E
1F
0L
1M
#150000000
0!
0"
02
03
0E
0F
0M
#155000000
1!
1"
12
13
1E
1F
1M
#160000000
0!
0"
02
03
0E
0F
0M
#165000000
1!
1"
12
13
1E
1F
1M
#170000000
0!
0"
02
03
0E
0F
0M
